{
"type": "FeatureCollection",
"name": "public_buildings",
"crs": { "type": "name", "properties": { "name": "urn:ogc:def:crs:OGC:1.3:CRS84" } },
"bbox": [ -78.7041103401443, 26.5110338385423, -78.6444075432226, 26.5369919782844 ],                                              
"features": [
{ "type": "Feature", "properties": { "Id": 0, "Type": null, "Descript": "Central Police Station", "BLDTYPE": "POLICE" }, "bbox": [ -78.696285007666745, 26.536991978284401, -78.696285007666745, 26.536991978284401 ], "geometry": { "type": "Point", "coordinates": [ -78.696285007666745, 26.536991978284401 ] } },
{ "type": "Feature", "properties": { "Id": 0, "Type": null, "Descript": "Bahamas Government Office Complex", "BLDTYPE": null }, "bbox": [ -78.694509456157334, 26.525473287719528, -78.694509456157334, 26.525473287719528 ], "geometry": { "type": "Point", "coordinates": [ -78.694509456157334, 26.525473287719528 ] } },
{ "type": "Feature", "properties": { "Id": 0, "Type": null, "Descript": "Garnet Lavarity Justice Centre", "BLDTYPE": null }, "bbox": [ -78.695393775093848, 26.536216355136812, -78.695393775093848, 26.536216355136812 ], "geometry": { "type": "Point", "coordinates": [ -78.695393775093848, 26.536216355136812 ] } },
{ "type": "Feature", "properties": { "Id": 0, "Type": null, "Descript": "National Insurance Building", "BLDTYPE": null }, "bbox": [ -78.694737285880294, 26.535650227838261, -78.694737285880294, 26.535650227838261 ], "geometry": { "type": "Point", "coordinates": [ -78.694737285880294, 26.535650227838261 ] } },
{ "type": "Feature", "properties": { "Id": 0, "Type": null, "Descript": "Rand Memorial Hospital", "BLDTYPE": null }, "bbox": [ -78.692523232492931, 26.532391582777095, -78.692523232492931, 26.532391582777095 ], "geometry": { "type": "Point", "coordinates": [ -78.692523232492931, 26.532391582777095 ] } },
{ "type": "Feature", "properties": { "Id": 0, "Type": null, "Descript": "Police Training College", "BLDTYPE": "POLICE" }, "bbox": [ -78.704110340144325, 26.528867376347087, -78.704110340144325, 26.528867376347087 ], "geometry": { "type": "Point", "coordinates": [ -78.704110340144325, 26.528867376347087 ] } },
{ "type": "Feature", "properties": { "Id": 0, "Type": null, "Descript": "Police Canteen", "BLDTYPE": "POLICE" }, "bbox": [ -78.701876238368143, 26.532579996708272, -78.701876238368143, 26.532579996708272 ], "geometry": { "type": "Point", "coordinates": [ -78.701876238368143, 26.532579996708272 ] } },
{ "type": "Feature", "properties": { "Id": 0, "Type": null, "Descript": "Lucaya Police Station", "BLDTYPE": "POLICE" }, "bbox": [ -78.644407543222556, 26.511033838542303, -78.644407543222556, 26.511033838542303 ], "geometry": { "type": "Point", "coordinates": [ -78.644407543222556, 26.511033838542303 ] } }
]
}
